microphone/__init__.py
microphone/__main__.py
microphone/command_manager.py
microphone/default_settings.ini
microphone/messaging.py
microphone/pyaudio_.py
microphone/resources/congo.aif
microphone/resources/congo.aiff
microphone/resources/congo.wav
microphone/resources/congo.wma
microphone/resources/done.wav
microphone-0.3.1.dist-info/METADATA
microphone-0.3.1.dist-info/RECORD
microphone-0.3.1.dist-info/WHEEL
microphone-0.3.1.dist-info/entry_points.txt
microphone-0.3.1.dist-info/top_level.txt
